multimodal_factory/__init__.py
multimodal_factory/adapters.py
multimodal_factory/config.py
multimodal_factory/core.py
multimodal_factory/factory.py
multimodal_factory/utils.py
mlm_factory-0.1.3.dist-info/METADATA
mlm_factory-0.1.3.dist-info/WHEEL
mlm_factory-0.1.3.dist-info/top_level.txt
mlm_factory-0.1.3.dist-info/RECORD
