Metadata-Version: 2.4
Name: mlm_factory
Version: 0.1.3
Summary: A multimodal factory library
Author-email: Wissem Karous <karouswissem@gmail.com>
Requires-Python: >=3.10
Dynamic: requires-python
